django_easy_drf/__init__.py
django_easy_drf/__main__.py
django_easy_drf/core.py
django_easy_drf/creator.py
django_easy_drf/drf_handlers.py
django_easy_drf/errors.py
django_easy_drf/import_handlers.py
django_easy_drf/main.py
django_easy_drf/models.py
django_easy_drf/serializers.py
django_easy_drf/urls.py
django_easy_drf/utils.py
django_easy_drf/views.py
django_easy_drf/templates/serializer
django_easy_drf/templates/serializers
django_easy_drf/templates/url
django_easy_drf/templates/urls
django_easy_drf/templates/views
django_easy_drf/templates/viewset
django_easy_drf-0.1.0.data/scripts/easy-drf
lib/__init__.py
lib/__main__.py
lib/creator.py
lib/models.py
lib/serializers.py
lib/urls.py
lib/views.py
django_easy_drf-0.1.0.dist-info/LICENSE
django_easy_drf-0.1.0.dist-info/METADATA
django_easy_drf-0.1.0.dist-info/WHEEL
django_easy_drf-0.1.0.dist-info/top_level.txt
django_easy_drf-0.1.0.dist-info/RECORD
